pysagas/__init__.py
pysagas/flow.py
pysagas/utilities.py
pysagas/cfd/__init__.py
pysagas/cfd/cart3d.py
pysagas/cfd/deck.py
pysagas/cfd/oblique_prandtl_meyer.py
pysagas/cfd/solver.py
pysagas/geometry/__init__.py
pysagas/geometry/cell.py
pysagas/geometry/parsers.py
pysagas/optimisation/__init__.py
pysagas/optimisation/optimiser.py
pysagas/optimisation/cart3d/__init__.py
pysagas/optimisation/cart3d/cart3d.py
pysagas/optimisation/cart3d/utilities.py
pysagas/optimisation/opm/__init__.py
pysagas/optimisation/opm/opm.py
pysagas/sensitivity/__init__.py
pysagas/sensitivity/calculator.py
pysagas/sensitivity/models.py
pysagas/sensitivity/cart3d/__init__.py
pysagas/sensitivity/cart3d/cart3d.py
pysagas/sensitivity/cart3d/utilities.py
hypysagas-0.15.3.dist-info/COPYING
hypysagas-0.15.3.dist-info/METADATA
hypysagas-0.15.3.dist-info/WHEEL
hypysagas-0.15.3.dist-info/top_level.txt
hypysagas-0.15.3.dist-info/RECORD
