Metadata-Version: 2.1
Name: hypysagas
Version: 0.15.3
Summary: Python Sensitivity Approximations for Geometric-Aerodynamic Surfaces
Author-email: Kieran Mackle <kemackle98@gmail.com>
Project-URL: Homepage, https://github.com/kieran-mackle/pysagas
Project-URL: Bug Tracker, https://github.com/kieran-mackle/pysagas/issues
Classifier: Programming Language :: Python :: 3
Classifier: License :: OSI Approved :: GNU General Public License v3 (GPLv3)
Classifier: Operating System :: OS Independent
Requires-Python: >=3.11
License-File: COPYING
Requires-Dist: numpy >=1.23.5
Requires-Dist: pandas >=1.5.2
Requires-Dist: tqdm >=4.64.1
Requires-Dist: art >=5.8
Requires-Dist: meshio >=5.3.4
Requires-Dist: matplotlib
Requires-Dist: scipy >=1.10.1
Requires-Dist: hypervehicle >=0.6.0
Provides-Extra: dev
Requires-Dist: sphinx ; extra == 'dev'
Requires-Dist: sphinx-rtd-theme ==1.1.1 ; extra == 'dev'
Requires-Dist: sphinx-copybutton >=0.5.0 ; extra == 'dev'
Requires-Dist: sphinx-inline-tabs >=2022.1.2b11 ; extra == 'dev'
Requires-Dist: myst-parser >=0.18.1 ; extra == 'dev'
Requires-Dist: sphinx-autobuild >=2021.3.14 ; extra == 'dev'
